privatebin/__init__.py
privatebin/__main__.py
privatebin/_core.py
privatebin/_crypto.py
privatebin/_enums.py
privatebin/_errors.py
privatebin/_models.py
privatebin/_utils.py
privatebin/_version.py
privatebin/_wrapper.py
privatebin/py.typed
privatebin/_cli/__init__.py
privatebin/_cli/_create.py
privatebin/_cli/_delete.py
privatebin/_cli/_get.py
privatebin-0.3.0.dist-info/METADATA
privatebin-0.3.0.dist-info/WHEEL
privatebin-0.3.0.dist-info/entry_points.txt
privatebin-0.3.0.dist-info/licenses/LICENSE
privatebin-0.3.0.dist-info/RECORD
