Metadata-Version: 2.4
Name: privatebin
Version: 0.3.0
Summary: Python library for interacting with PrivateBin's v2 API (PrivateBin >= 1.3) to create, retrieve, and delete encrypted pastes.
Project-URL: Repository, https://github.com/Ravencentric/privatebin
Project-URL: Documentation, https://ravencentric.cc/privatebin/
Author-email: Ravencentric <me@ravencentric.cc>
License-Expression: MIT
License-File: LICENSE
Keywords: paste,pastebin,privatebin
Classifier: Intended Audience :: Developers
Classifier: Operating System :: OS Independent
Classifier: Programming Language :: Python :: 3.10
Classifier: Programming Language :: Python :: 3.11
Classifier: Programming Language :: Python :: 3.12
Classifier: Programming Language :: Python :: 3.13
Classifier: Programming Language :: Python :: Implementation :: CPython
Classifier: Typing :: Typed
Requires-Python: >=3.10
Requires-Dist: base58>=2.1.1
Requires-Dist: cryptography>=44.0.2
Requires-Dist: httpx>=0.28.1
Requires-Dist: msgspec>=0.19.0
Provides-Extra: cli
Requires-Dist: cyclopts>=3.10.0; extra == 'cli'
Requires-Dist: rich>=13.9.4; extra == 'cli'
